odoo10_addon_mrp_sale_info-10.0.1.0.0.99.dev6-nspkg.pth
odoo/addons/mrp_sale_info/README.rst
odoo/addons/mrp_sale_info/__init__.py
odoo/addons/mrp_sale_info/__manifest__.py
odoo/addons/mrp_sale_info/i18n/de.po
odoo/addons/mrp_sale_info/i18n/es.po
odoo/addons/mrp_sale_info/i18n/es_MX.po
odoo/addons/mrp_sale_info/i18n/fr.po
odoo/addons/mrp_sale_info/i18n/mrp_sale_info.pot
odoo/addons/mrp_sale_info/i18n/pt_BR.po
odoo/addons/mrp_sale_info/i18n/zh_CN.po
odoo/addons/mrp_sale_info/models/__init__.py
odoo/addons/mrp_sale_info/models/mrp_production.py
odoo/addons/mrp_sale_info/models/mrp_workorder.py
odoo/addons/mrp_sale_info/models/procurement.py
odoo/addons/mrp_sale_info/static/description/icon.png
odoo/addons/mrp_sale_info/tests/__init__.py
odoo/addons/mrp_sale_info/tests/test_sale_manufacture.py
odoo/addons/mrp_sale_info/views/mrp_production.xml
odoo/addons/mrp_sale_info/views/mrp_workorder.xml
odoo10_addon_mrp_sale_info-10.0.1.0.0.99.dev6.dist-info/METADATA
odoo10_addon_mrp_sale_info-10.0.1.0.0.99.dev6.dist-info/WHEEL
odoo10_addon_mrp_sale_info-10.0.1.0.0.99.dev6.dist-info/namespace_packages.txt
odoo10_addon_mrp_sale_info-10.0.1.0.0.99.dev6.dist-info/top_level.txt
odoo10_addon_mrp_sale_info-10.0.1.0.0.99.dev6.dist-info/RECORD
