Metadata-Version: 2.1
Name: odoo10-addon-mrp-sale-info
Version: 10.0.1.0.0.99.dev6
Summary: Adds sale information to Manufacturing models
Home-page: http://www.antiun.com
License: AGPL-3
Platform: UNKNOWN
Classifier: Programming Language :: Python
Classifier: Framework :: Odoo
Classifier: License :: OSI Approved :: GNU Affero General Public License v3
Requires-Python: ~=2.7
Requires-Dist: odoo (<10.1dev,>=10.0)
